esi/__init__.py
esi/admin.py
esi/app_settings.py
esi/apps.py
esi/checks.py
esi/clients.py
esi/decorators.py
esi/errors.py
esi/exceptions.py
esi/helpers.py
esi/managers.py
esi/managers.pyi
esi/models.py
esi/openapi_clients.py
esi/rate_limiting.py
esi/signals.py
esi/stubs.py
esi/stubs.pyi
esi/tasks.py
esi/urls.py
esi/views.py
esi/aiopenapi3/client.py
esi/aiopenapi3/plugins.py
esi/locale/cs_CZ/LC_MESSAGES/django.mo
esi/locale/cs_CZ/LC_MESSAGES/django.po
esi/locale/de/LC_MESSAGES/django.mo
esi/locale/de/LC_MESSAGES/django.po
esi/locale/en/LC_MESSAGES/django.mo
esi/locale/en/LC_MESSAGES/django.po
esi/locale/es/LC_MESSAGES/django.mo
esi/locale/es/LC_MESSAGES/django.po
esi/locale/fr_FR/LC_MESSAGES/django.mo
esi/locale/fr_FR/LC_MESSAGES/django.po
esi/locale/it_IT/LC_MESSAGES/django.mo
esi/locale/it_IT/LC_MESSAGES/django.po
esi/locale/ja/LC_MESSAGES/django.mo
esi/locale/ja/LC_MESSAGES/django.po
esi/locale/ko_KR/LC_MESSAGES/django.mo
esi/locale/ko_KR/LC_MESSAGES/django.po
esi/locale/nl_NL/LC_MESSAGES/django.mo
esi/locale/nl_NL/LC_MESSAGES/django.po
esi/locale/pl_PL/LC_MESSAGES/django.mo
esi/locale/pl_PL/LC_MESSAGES/django.po
esi/locale/ru/LC_MESSAGES/django.mo
esi/locale/ru/LC_MESSAGES/django.po
esi/locale/sk/LC_MESSAGES/django.mo
esi/locale/sk/LC_MESSAGES/django.po
esi/locale/uk/LC_MESSAGES/django.mo
esi/locale/uk/LC_MESSAGES/django.po
esi/locale/zh_Hans/LC_MESSAGES/django.mo
esi/locale/zh_Hans/LC_MESSAGES/django.po
esi/management/commands/__init__.py
esi/management/commands/esi_clear_spec_cache.py
esi/management/commands/generate_esi_stubs.py
esi/management/commands/migrate_to_ssov2.py
esi/migrations/0001_initial.py
esi/migrations/0002_scopes_20161208.py
esi/migrations/0003_hide_tokens_from_admin_site.py
esi/migrations/0004_remove_unique_access_token.py
esi/migrations/0005_remove_token_length_limit.py
esi/migrations/0006_remove_url_length_limit.py
esi/migrations/0007_fix_mysql_8_migration.py
esi/migrations/0008_nullable_refresh_token.py
django_esi-8.2.2.dist-info/licenses/LICENSE
django_esi-8.2.2.dist-info/WHEEL
django_esi-8.2.2.dist-info/METADATA
django_esi-8.2.2.dist-info/RECORD
