Metadata-Version: 2.4
Name: django-esi
Version: 8.2.2
Summary: Django app for accessing the EVE Swagger Interface (ESI).
Keywords: eveonline
Author-email: Alliance Auth <adarnof@gmail.com>
Requires-Python: >=3.10
Classifier: Environment :: Web Environment
Classifier: Framework :: Django
Classifier: Framework :: Django :: 4.2
Classifier: Framework :: Django :: 5.2
Classifier: Intended Audience :: Developers
Classifier: License :: OSI Approved :: GNU General Public License v3 (GPLv3)
Classifier: Operating System :: OS Independent
Classifier: Programming Language :: Python
Classifier: Programming Language :: Python :: 3 :: Only
Classifier: Programming Language :: Python :: 3.10
Classifier: Programming Language :: Python :: 3.11
Classifier: Programming Language :: Python :: 3.12
Classifier: Programming Language :: Python :: 3.13
Classifier: Programming Language :: Python :: 3.14
Classifier: Topic :: Internet :: WWW/HTTP
Classifier: Topic :: Internet :: WWW/HTTP :: Dynamic Content
License-File: LICENSE
Requires-Dist: aiopenapi3
Requires-Dist: bravado>=10.6,<12
Requires-Dist: celery>=4.0.2
Requires-Dist: django>=4.2,<6
Requires-Dist: django-redis>=5.2
Requires-Dist: httpx[brotli, http2, zstd]
Requires-Dist: jsonschema<4
Requires-Dist: python-jose>=3.3
Requires-Dist: requests>=2.26
Requires-Dist: requests-oauthlib>=0.8
Requires-Dist: tenacity
Requires-Dist: tqdm>=4.62.3
Requires-Dist: myst-parser ; extra == "docs"
Requires-Dist: sphinx ; extra == "docs"
Requires-Dist: sphinx-copybutton ; extra == "docs"
Requires-Dist: sphinx-rtd-theme>=3,<4 ; extra == "docs"
Requires-Dist: sphinx-tabs ; extra == "docs"
Requires-Dist: sphinxcontrib-django ; extra == "docs"
Requires-Dist: coverage ; extra == "test"
Requires-Dist: factory-boy ; extra == "test"
Requires-Dist: requests-mock ; extra == "test"
Project-URL: Documentation, https://django-esi.readthedocs.io/en/latest/
Project-URL: Homepage, https://gitlab.com/allianceauth/django-esi
Project-URL: Source, https://gitlab.com/allianceauth/django-esi
Project-URL: Tracker, https://gitlab.com/allianceauth/django-esi/-/issues
Provides-Extra: docs
Provides-Extra: test
